{"title":"Publish","date":"2018-03-03T08:29:52.000Z","updated":"2020-05-10T04:18:58.804Z","comments":true,"path":"api/pages/publish/index.json","covers":null,"excerpt":"","content":"<link rel=\"stylesheet\" class=\"aplayer-secondary-style-marker\" href=\"\\assets\\css\\APlayer.min.css\"><script src=\"\\assets\\js\\APlayer.min.js\" class=\"aplayer-secondary-script-marker\"></script><ol>\n<li>xxxx, Acta, 2020</li>\n<li>xxxx, Science, 2020</li>\n<li>xxxx, Nature, 2020</li>\n</ol>\n<link rel=\"stylesheet\" href=\"/css/spoiler.css\" type=\"text/css\"><script src=\"/js/spoiler.js\" type=\"text/javascript\" async></script>"}